ai/__init__.py
ai/nlp/__init__.py
ai/nlp/time/__init__.py
ai/nlp/time/parse/LunarSolarConverter.py
ai/nlp/time/parse/RangeTimeEnum.py
ai/nlp/time/parse/StringPreHandler.py
ai/nlp/time/parse/Test.py
ai/nlp/time/parse/TimeNormalizer.py
ai/nlp/time/parse/TimePoint.py
ai/nlp/time/parse/TimeUnit.py
ai/nlp/time/parse/__init__.py
ai/nlp/time/parse/resource/__init__.py
ai/nlp/time/parse/resource/regex.txt
common/__init__.py
common/main.py
common/utils/__init__.py
common/utils/download.py
common/utils/sort.py
common/utils/xlsx.py
test/__init__.py
test/test1.py
gediao_utils-0.0.7.dist-info/METADATA
gediao_utils-0.0.7.dist-info/WHEEL
gediao_utils-0.0.7.dist-info/top_level.txt
gediao_utils-0.0.7.dist-info/RECORD
