Metadata-Version: 2.1
Name: gediao-utils
Version: 0.0.7
Summary: xuxy utils package
Home-page: https://gitee.com/ukihi/gediao-open-python-utils
Author: 色调呀
Author-email: 1059738716@qq.com
